hornwitser/factorio_tools/__init__.py
hornwitser/factorio_tools/__main__.py
hornwitser/factorio_tools/desync.py
hornwitser/factorio_tools/disown.py
hornwitser/factorio_tools/multi.py
hornwitser/factorio_tools/parse.py
hornwitser/factorio_tools/ping.py
hornwitser_factorio_tools-0.0.7.dist-info/licenses/LICENSE.txt
hornwitser_factorio_tools-0.0.7.dist-info/METADATA
hornwitser_factorio_tools-0.0.7.dist-info/WHEEL
hornwitser_factorio_tools-0.0.7.dist-info/top_level.txt
hornwitser_factorio_tools-0.0.7.dist-info/zip-safe
hornwitser_factorio_tools-0.0.7.dist-info/RECORD
