Metadata-Version: 2.4
Name: hornwitser.factorio_tools
Version: 0.0.7
Summary: Tools for Debugging Factorio
Home-page: https://github.com/Hornwitser/factorio_tools
Author: Hornwitser
Author-email: github@hornwitser.no
Classifier: Development Status :: 3 - Alpha
Classifier: Intended Audience :: Developers
Classifier: Environment :: Console
Classifier: License :: OSI Approved :: GNU General Public License v3 or later (GPLv3+)
Classifier: Programming Language :: Python :: 3
Classifier: Operating System :: Microsoft :: Windows
Classifier: Topic :: Utilities
Requires-Python: >=3.7
License-File: LICENSE.txt
Requires-Dist: construct>=2.10.53
Dynamic: license-file
